mt940/__about__.py
mt940/__init__.py
mt940/_compat.py
mt940/json.py
mt940/models.py
mt940/parser.py
mt940/processors.py
mt940/tags.py
mt940/utils.py
mt_940-4.30.0.dist-info/AUTHORS.rst
mt_940-4.30.0.dist-info/LICENSE
mt_940-4.30.0.dist-info/METADATA
mt_940-4.30.0.dist-info/WHEEL
mt_940-4.30.0.dist-info/top_level.txt
mt_940-4.30.0.dist-info/RECORD
