Metadata-Version: 2.1
Name: mt-940
Version: 4.30.0
Summary: A library to parse MT940 files and returns smart Python collections for statistics and manipulation.
Home-page: https://github.com/WoLpH/mt940
Author: Rick van Hattem (wolph)
Author-email: wolph@wol.ph
License: BSD
Keywords: MT940
Classifier: Development Status :: 6 - Mature
Classifier: Intended Audience :: Developers
Classifier: License :: OSI Approved :: BSD License
Classifier: Natural Language :: English
Classifier: Programming Language :: Python :: 3
Classifier: Programming Language :: Python :: 3.7
Classifier: Programming Language :: Python :: 3.8
Classifier: Programming Language :: Python :: 3.9
Classifier: Programming Language :: Python :: 3.10
Classifier: Programming Language :: Python :: Implementation :: PyPy
Provides-Extra: docs
Provides-Extra: tests
License-File: LICENSE
License-File: AUTHORS.rst
